asyncify/__about__.py
asyncify/__init__.py
asyncify/__main__.py
asyncify/_anyio.py
asyncify/aios/__init__.py
asyncify/aios/_path.py
asyncify/core.py
asyncify/py.typed
asyncify-0.12.0.dist-info/WHEEL
asyncify-0.12.0.dist-info/METADATA
asyncify-0.12.0.dist-info/RECORD
