Metadata-Version: 2.3
Name: asyncify
Version: 0.12.0
Summary: sync 2 async
Keywords: async,asyncify,asyncio,dgpy
Author: jesse
Author-email: jesse <jesse@dgi.com>
Classifier: Development Status :: 5 - Production/Stable
Classifier: Intended Audience :: Developers
Classifier: License :: OSI Approved :: MIT License
Classifier: Programming Language :: Python
Classifier: Programming Language :: Python :: 3 :: Only
Classifier: Programming Language :: Python :: 3.11
Classifier: Programming Language :: Python :: 3.12
Classifier: Programming Language :: Python :: 3.13
Classifier: Typing :: Typed
Requires-Dist: funkify>=0.7
Requires-Python: >=3.11, <4.0
